{
    "streams": [
        {
            "index": 0,
            "codec_name": "hevc",
            "codec_long_name": "H.265 / HEVC (High Efficiency Video Coding)",
            "profile": "Main 10",
            "codec_type": "video",
            "codec_tag_string": "[0][0][0][0]",
            "codec_tag": "0x0000",
            "width": 1920,
            "height": 1080,
            "coded_width": 1920,
            "coded_height": 1080,
            "has_b_frames": 2,
            "sample_aspect_ratio": "1:1",
            "display_aspect_ratio": "16:9",
            "pix_fmt": "yuv420p10le",
            "level": 120,
            "color_range": "tv",
            "color_space": "bt2020nc",
            "color_transfer": "smpte2084",
            "color_primaries": "bt2020",
            "chroma_location": "left",
            "field_order": "progressive",
            "view_ids_available": "",
            "view_pos_available": "",
            "r_frame_rate": "24000/1001",
            "avg_frame_rate": "24000/1001",
            "time_base": "1/1000",
            "start_pts": 0,
            "start_time": "0.000000",
            "extradata_size": 2581,
            "disposition": {
                "default": 0,
                "dub": 0,
                "original": 0,
                "comment": 0,
                "lyrics": 0,
                "karaoke": 0,
                "forced": 0,
                "hearing_impaired": 0,
                "visual_impaired": 0,
                "clean_effects": 0,
                "attached_pic": 0,
                "timed_thumbnails": 0,
                "non_diegetic": 0,
                "captions": 0,
                "descriptions": 0,
                "metadata": 0,
                "dependent": 0,
                "still_image": 0,
                "multilayer": 0
            },
            "tags": {
                "ENCODER": "Lavc62.28.102 libx265",
                "DURATION": "00:00:14.848000000"
            }
        },
        {
            "index": 1,
            "codec_name": "hdmv_pgs_subtitle",
            "codec_long_name": "HDMV Presentation Graphic Stream subtitles",
            "codec_type": "subtitle",
            "codec_tag_string": "[0][0][0][0]",
            "codec_tag": "0x0000",
            "width": 1920,
            "height": 1080,
            "r_frame_rate": "0/0",
            "avg_frame_rate": "0/0",
            "time_base": "1/1000",
            "start_pts": 0,
            "start_time": "0.000000",
            "disposition": {
                "default": 1,
                "dub": 0,
                "original": 0,
                "comment": 0,
                "lyrics": 0,
                "karaoke": 0,
                "forced": 0,
                "hearing_impaired": 0,
                "visual_impaired": 0,
                "clean_effects": 0,
                "attached_pic": 0,
                "timed_thumbnails": 0,
                "non_diegetic": 0,
                "captions": 0,
                "descriptions": 0,
                "metadata": 0,
                "dependent": 0,
                "still_image": 0,
                "multilayer": 0
            },
            "tags": {
                "language": "chi",
                "title": "PGS image subtitles",
                "_STATISTICS_TAGS": "BPS DURATION NUMBER_OF_FRAMES NUMBER_OF_BYTES SOURCE_ID",
                "BPS": "798002",
                "NUMBER_OF_FRAMES": "85",
                "NUMBER_OF_BYTES": "1497652",
                "SOURCE_ID": "0012A4",
                "_STATISTICS_WRITING_APP": "mkvmerge v94.0 ('Initiate') 64-bit",
                "_STATISTICS_WRITING_DATE_UTC": "2026-07-24 11:22:05",
                "DURATION": "00:00:15.014000000"
            }
        }
    ],
    "format": {
        "filename": ".codex-build\\issue-attachments\\hdr10-pgs-synthetic-sample.mkv",
        "nb_streams": 2,
        "nb_programs": 0,
        "nb_stream_groups": 0,
        "format_name": "matroska,webm",
        "format_long_name": "Matroska / WebM",
        "start_time": "0.000000",
        "duration": "15.014000",
        "size": "1552640",
        "bit_rate": "827302",
        "probe_score": 100,
        "tags": {
            "ENCODER": "Lavf62.12.102"
        }
    }
}
